mcp_tree_explorer/__init__.py
mcp_tree_explorer/main.py
mcp_tree_explorer/tree_utils.py
mcp_tree_explorer-0.1.4.dist-info/METADATA
mcp_tree_explorer-0.1.4.dist-info/WHEEL
mcp_tree_explorer-0.1.4.dist-info/entry_points.txt
mcp_tree_explorer-0.1.4.dist-info/top_level.txt
mcp_tree_explorer-0.1.4.dist-info/RECORD
