Metadata-Version: 2.2
Name: mcp-tree-explorer
Version: 0.1.4
Summary: MCP tool that provides directory tree visualization for Cursor
Author-email: Carter LaSalle <carterlasalle@gmail.com>
Project-URL: Homepage, https://github.com/carterlasalle/directory_structure_mcp
Project-URL: Bug Tracker, https://github.com/carterlasalle/directory_structure_mcp/issues
Project-URL: Source, https://github.com/carterlasalle/directory_structure_mcp
Keywords: mcp,tree,directory,visualization,cursor
Classifier: Development Status :: 3 - Alpha
Classifier: Intended Audience :: Developers
Classifier: License :: OSI Approved :: MIT License
Classifier: Programming Language :: Python :: 3
Classifier: Programming Language :: Python :: 3.8
Classifier: Programming Language :: Python :: 3.9
Classifier: Programming Language :: Python :: 3.10
Classifier: Programming Language :: Python :: 3.11
Classifier: Topic :: Software Development :: Libraries :: Python Modules
Classifier: Topic :: Utilities
Requires-Python: >=3.8
Requires-Dist: mcp[cli]
Provides-Extra: dev
Requires-Dist: pytest>=7.0.0; extra == "dev"
Requires-Dist: black>=23.0.0; extra == "dev"
Requires-Dist: isort>=5.10.0; extra == "dev"
Requires-Dist: mypy>=1.0.0; extra == "dev"
